{
	"cluster": [],
	"indices": [{
		"names": [
			"auth*"
		],
		"privileges": [
			"read"
		],
		"field_security": {
			"grant": [
				"*"
			],
			"except": []
		},
		"allow_restricted_indices": false
	}],
	"applications": [{
		"application": "kibana-.kibana",
		"privileges": [
			"feature_discover.read"
		],
		"resources": [
			"space:external-view"
		]
	}],
	"run_as": [],
	"metadata": {
		"version":     1,
		"description": "Deployed with Ansible"
	},
	"transient_metadata": {
		"enabled": true
	}
}
